spice2sch/__init__.py
spice2sch/__main__.py
spice2sch/cli_def.py
spice2sch/constants.py
spice2sch/main.py
spice2sch/models.py
spice2sch/spice.py
spice2sch-0.1.1.dist-info/METADATA
spice2sch-0.1.1.dist-info/WHEEL
spice2sch-0.1.1.dist-info/entry_points.txt
spice2sch-0.1.1.dist-info/RECORD
